telelog/__init__.py
telelog/__init__.pyi
telelog/py.typed
telelog/telelog.cp39-win_amd64.pyd
telelog_python-0.3.0.dist-info/METADATA
telelog_python-0.3.0.dist-info/WHEEL
telelog_python-0.3.0.dist-info/RECORD
