Metadata-Version: 2.4
Name: telelog-python
Version: 0.3.0
Classifier: Development Status :: 4 - Beta
Classifier: Intended Audience :: Developers
Classifier: License :: OSI Approved :: MIT License
Classifier: License :: OSI Approved :: Apache Software License
Classifier: Programming Language :: Python :: 3
Classifier: Programming Language :: Python :: 3.8
Classifier: Programming Language :: Python :: 3.9
Classifier: Programming Language :: Python :: 3.10
Classifier: Programming Language :: Python :: 3.11
Classifier: Programming Language :: Python :: 3.12
Classifier: Programming Language :: Python :: 3.13
Classifier: Programming Language :: Rust
Classifier: Topic :: Software Development :: Libraries :: Python Modules
Classifier: Topic :: System :: Logging
Classifier: Topic :: Software Development :: Debuggers
Classifier: Typing :: Typed
Summary: High-performance structured logging library with rich visualization capabilities
Keywords: logging,structured,profiling,visualization,performance,monitoring
Home-Page: https://github.com/vedant-asati03/telelog
Author-email: Vedant Asati <vedant.asati03@gmail.com>
License: MIT OR Apache-2.0
Requires-Python: >=3.8
Project-URL: Homepage, https://github.com/vedant-asati03/telelog
Project-URL: Repository, https://github.com/vedant-asati03/telelog
Project-URL: Bug Reports, https://github.com/vedant-asati03/telelog/issues
Project-URL: Documentation, https://github.com/vedant-asati03/telelog#readme
